reqdbcontentcreator/__init__.py
reqdbcontentcreator/__main__.py
reqdbcontentcreator/rollback.py
reqdbcontentcreator/sources.py
reqdbcontentcreator-1.0.4.dist-info/LICENSE
reqdbcontentcreator-1.0.4.dist-info/METADATA
reqdbcontentcreator-1.0.4.dist-info/WHEEL
reqdbcontentcreator-1.0.4.dist-info/entry_points.txt
reqdbcontentcreator-1.0.4.dist-info/RECORD
