Metadata-Version: 2.3
Name: reqdbcontentcreator
Version: 1.0.4
Summary: 
Author: Fischer, Daniel-MGB
Author-email: daniel.fischer@mgb.ch
Requires-Python: >=3.10,<4.0
Classifier: Programming Language :: Python :: 3
Classifier: Programming Language :: Python :: 3.10
Classifier: Programming Language :: Python :: 3.11
Classifier: Programming Language :: Python :: 3.12
Classifier: Programming Language :: Python :: 3.13
Requires-Dist: argparse (>=1.4.0,<2.0.0)
Requires-Dist: excelextractor (>=0.1.0,<0.2.0)
Requires-Dist: msal (>=1.31.0,<2.0.0)
Requires-Dist: pypandoc (>=1.14,<2.0)
Requires-Dist: pyyaml (>=6.0.2,<7.0.0)
Requires-Dist: reqdb (>=0.7.0,<0.8.0)
Requires-Dist: requests (>=2.32.3,<3.0.0)
